ENGRAVEAlerts/.DS_Store
ENGRAVEAlerts/__init__.py
ENGRAVEAlerts/__version__.py
ENGRAVEAlerts/cl_utils.py
ENGRAVEAlerts/default_settings.yaml
ENGRAVEAlerts/gcnListener.py
ENGRAVEAlerts/gcnNoticeParser.py
ENGRAVEAlerts/setup.cfg
ENGRAVEAlerts/sms.py
ENGRAVEAlerts/utKit.py
ENGRAVEAlerts/voicecall.py
ENGRAVEAlerts/commonutils/__init__.py
ENGRAVEAlerts/commonutils/getpackagepath.py
ENGRAVEAlerts/tests/.DS_Store
ENGRAVEAlerts/tests/__init__.py
ENGRAVEAlerts/tests/test_gcnListener.py
ENGRAVEAlerts/tests/test_gcnNoticeParser.py
ENGRAVEAlerts/tests/test_sms.py
ENGRAVEAlerts/tests/test_voicecall.py
ENGRAVEAlerts/tests/input/.DS_Store
ENGRAVEAlerts/tests/input/Initial-VOEvent.xml
ENGRAVEAlerts/tests/input/Preliminary-VOEvent.xml
ENGRAVEAlerts/tests/input/Retraction-VOEvent.xml
ENGRAVEAlerts/tests/input/Update-VOEvent.xml
ENGRAVEAlerts/tests/input/example_settings.yaml
ENGRAVEAlerts/tests/output/.DS_Store
ENGRAVEAlerts/tests/output/Initial-VOEvent.xml
ENGRAVEAlerts/tests/output/Preliminary-VOEvent.xml
ENGRAVEAlerts/tests/output/Retraction-VOEvent.xml
ENGRAVEAlerts/tests/output/Update-VOEvent.xml
ENGRAVEAlerts/tests/output/example_settings.yaml
ENGRAVEAlerts-0.2.0.dist-info/DESCRIPTION.rst
ENGRAVEAlerts-0.2.0.dist-info/METADATA
ENGRAVEAlerts-0.2.0.dist-info/RECORD
ENGRAVEAlerts-0.2.0.dist-info/WHEEL
ENGRAVEAlerts-0.2.0.dist-info/entry_points.txt
ENGRAVEAlerts-0.2.0.dist-info/metadata.json
ENGRAVEAlerts-0.2.0.dist-info/top_level.txt
