Metadata-Version: 2.0
Name: ENGRAVEAlerts
Version: 0.2.0
Summary: A python package and command-line tools to Alerting and Notification Tools for ENGRAVE Team
Home-page: https://github.com/thespacedoctor/ENGRAVEAlerts
Author: David Young
Author-email: davidrobertyoung@gmail.com
License: MIT
Download-URL: https://github.com/thespacedoctor/ENGRAVEAlerts/archive/v0.2.0.zip
Keywords: engrave, notifications, alerts
Platform: UNKNOWN
Classifier: Development Status :: 4 - Beta
Classifier: License :: OSI Approved :: MIT License
Classifier: Programming Language :: Python :: 2.7
Classifier: Topic :: Utilities
Requires-Dist: ENGRAVEAlerts
Requires-Dist: bitly-api
Requires-Dist: fundamentals
Requires-Dist: pygcn
Requires-Dist: pyyaml
Requires-Dist: requests
Requires-Dist: twilio
